{
  "config": {
    "step": {
      "user": {
        "title": "Add Cover Time Based",
        "description": "Configure a time-based cover with position maps.\n\n**Entity Options:**\n- **Use Existing Cover**: Control an existing cover entity\n- **Use Individual Switches**: Control via separate open/close/stop entities\n\n**Time Maps:** Define position at specific time intervals in JSON format. Keys without quotes are supported.\n\nExamples:\n- Opening: {opening_example}\n- Closing: {closing_example}\n- Alternative: {0: 0, 5: 50, 10: 100}\n\n**Note**: Tilt times are optional - leave empty if not needed.",
        "data": {
          "name": "Name",
          "use_existing_cover": "Use Existing Cover (instead of individual switches)",
          "cover_entity_id": "Cover Entity (when using existing cover)",
          "open_switch_entity_id": "Open Entity (Switch/Script/Automation)",
          "close_switch_entity_id": "Close Entity (Switch/Script/Automation)",
          "stop_switch_entity_id": "Stop Entity (Optional)",
          "is_button": "Entities are buttons/momentary (auto turn off)",
          "opening_time_map": "Opening Time Map (JSON format)",
          "closing_time_map": "Closing Time Map (JSON format)",
          "tilting_time_down": "Tilt Down Time (seconds, optional)",
          "tilting_time_up": "Tilt Up Time (seconds, optional)"
        }
      },
      "reconfigure": {
        "title": "Reconfigure Cover Time Based",
        "description": "Update the configuration for this cover.\n\n**Entity Options:**\n- **Use Existing Cover**: Control an existing cover entity\n- **Use Individual Switches**: Control via separate open/close/stop entities\n\nTime maps define position at specific time intervals in JSON format:\n- Opening example: {opening_example}\n- Closing example: {closing_example}",
        "data": {
          "name": "Name",
          "use_existing_cover": "Use Existing Cover (instead of individual switches)",
          "cover_entity_id": "Cover Entity (when using existing cover)",
          "open_switch_entity_id": "Open Entity (Switch/Script/Automation)",
          "close_switch_entity_id": "Close Entity (Switch/Script/Automation)",
          "stop_switch_entity_id": "Stop Entity (Optional)",
          "is_button": "Entities are buttons/momentary (auto turn off)",
          "opening_time_map": "Opening Time Map (JSON)",
          "closing_time_map": "Closing Time Map (JSON)",
          "tilting_time_down": "Tilt Down Time (seconds, leave empty to disable)",
          "tilting_time_up": "Tilt Up Time (seconds, leave empty to disable)"
        }
      }
    },
    "error": {
      "unknown": "Unexpected error occurred",
      "invalid_time_map": "Invalid time map format"
    },
    "abort": {
      "already_configured": "Cover with this name is already configured",
      "reconfigure_successful": "Configuration updated successfully"
    }
  },
  "options": {
    "step": {
      "init": {
        "title": "Cover Time Based Options",
        "description": "Configure advanced options for the cover.",
        "data": {
          "tilting_time_down": "Tilt Down Time (seconds)",
          "tilting_time_up": "Tilt Up Time (seconds)"
        }
      }
    }
  },
  "services": {
    "set_known_position": {
      "name": "Set cover position",
      "description": "Sets a known position for the cover internally.",
      "fields": {
        "entity_id": {
          "name": "Entity ID",
          "description": "The entity ID of the cover to set the position for."
        },
        "position": {
            "name": "Position",
            "description": "The position of the cover, between 0 and 100."
        }
      }
    },
    "set_known_tilt_position": {
      "name": "Set cover tilt position",
      "description": "Sets a known tilt position for the cover internally.",
      "fields": {
        "entity_id": {
          "name": "Entity ID",
          "description": "The entity ID of the cover to set the tilt position for."
        },
        "position": {
            "name": "Position",
            "description": "The tilt position of the cover, between 0 and 100."
        }
      }
    }
  }
}